{"region": {"center": {"latitude": 40.7858388083, "longitude": -73.9766614504}}, "total": 3700, "businesses": [{"rating": 4.0, "review_count": 695, "name": "Fred's Restaurant", "transactions": ["pickup", "delivery"], "url": "https://www.yelp.com/biz/freds-restaurant-new-york-3?adjust_creative=yhLoLzsNXKw40xZ5RCWPpA&utm_campaign=yelp_api_v3&utm_medium=api_v3_business_search&utm_source=yhLoLzsNXKw40xZ5RCWPpA", "price": "$$", "distance": 14.312663231861244, "coordinates": {"latitude": 40.7856233, "longitude": -73.9767067}, "alias": "freds-restaurant-new-york-3", "image_url": "https://s3-media2.fl.yelpcdn.com/bphoto/esmn2zHEbbMcBTg7JZkueQ/o.jpg", "categories": [{"alias": "breakfast_brunch", "title": "Breakfast & Brunch"}, {"alias": "tradamerican", "title": "American (Traditional)"}, {"alias": "bars", "title": "Bars"}], "display_phone": "(212) 579-3076", "phone": "+12125793076", "id": "cSRzfprFfAnT1nAcQMgrDA", "is_closed": false, "location": {"city": "New York", "display_address": ["476 Amsterdam Ave", "New York, NY 10024"], "country": "US", "address2": "", "address3": "", "state": "NY", "address1": "476 Amsterdam Ave", "zip_code": "10024"}}]}