{"region": {"center": {"latitude": 40.68002534, "longitude": -73.9745064157}}, "total": 3300, "businesses": [{"rating": 3.5, "review_count": 667, "name": "Morgan's Barbecue", "transactions": ["delivery", "pickup"], "url": "https://www.yelp.com/biz/morgans-brooklyn-barbecue-brooklyn-2?adjust_creative=yhLoLzsNXKw40xZ5RCWPpA&utm_campaign=yelp_api_v3&utm_medium=api_v3_business_search&utm_source=yhLoLzsNXKw40xZ5RCWPpA", "price": "$$", "distance": 38.47236161354707, "coordinates": {"latitude": 40.679879, "longitude": -73.974093}, "alias": "morgans-brooklyn-barbecue-brooklyn-2", "image_url": "https://s3-media3.fl.yelpcdn.com/bphoto/pSPIYnUREUHL3jYap0OCFg/o.jpg", "categories": [{"alias": "bbq", "title": "Barbeque"}, {"alias": "bars", "title": "Bars"}, {"alias": "breakfast_brunch", "title": "Breakfast & Brunch"}], "display_phone": "(718) 622-2224", "phone": "+17186222224", "id": "fcGhPwDpEzo8sLXquK349w", "is_closed": false, "location": {"city": "Brooklyn", "display_address": ["267 Flatbush Ave", "Brooklyn, NY 11217"], "country": "US", "address2": null, "address3": "", "state": "NY", "address1": "267 Flatbush Ave", "zip_code": "11217"}}]}