{"region": {"center": {"latitude": 40.7557548217, "longitude": -73.8835079097}}, "total": 2500, "businesses": [{"rating": 3.0, "review_count": 8, "name": "Colombia Con Sabor", "transactions": ["delivery", "pickup"], "url": "https://www.yelp.com/biz/colombia-con-sabor-queens?adjust_creative=yhLoLzsNXKw40xZ5RCWPpA&utm_campaign=yelp_api_v3&utm_medium=api_v3_business_search&utm_source=yhLoLzsNXKw40xZ5RCWPpA", "price": "$$", "distance": 30.402595484975727, "coordinates": {"latitude": 40.75599, "longitude": -73.88375}, "alias": "colombia-con-sabor-queens", "image_url": "https://s3-media4.fl.yelpcdn.com/bphoto/HhOi7BMXl7bKKCwgPj9qog/o.jpg", "categories": [{"alias": "colombian", "title": "Colombian"}, {"alias": "cocktailbars", "title": "Cocktail Bars"}, {"alias": "icecream", "title": "Ice Cream & Frozen Yogurt"}], "display_phone": "(718) 205-7000", "phone": "+17182057000", "id": "8iUuCqFQnJ6t1nI5_GLDFA", "is_closed": false, "location": {"city": "Queens", "display_address": ["83-17 Northern Blvd", "Queens, NY 11372"], "country": "US", "address2": null, "address3": "", "state": "NY", "address1": "83-17 Northern Blvd", "zip_code": "11372"}}]}