{"region": {"center": {"latitude": 40.762422658, "longitude": -73.9902859421}}, "total": 3900, "businesses": [{"rating": 4.0, "review_count": 85, "name": "Gaf West", "transactions": [], "url": "https://www.yelp.com/biz/gaf-west-new-york?adjust_creative=yhLoLzsNXKw40xZ5RCWPpA&utm_campaign=yelp_api_v3&utm_medium=api_v3_business_search&utm_source=yhLoLzsNXKw40xZ5RCWPpA", "price": "$", "distance": 13.302461512716322, "coordinates": {"latitude": 40.76245, "longitude": -73.99011}, "alias": "gaf-west-new-york", "image_url": "https://s3-media3.fl.yelpcdn.com/bphoto/oFb2GxkQvfqLkeM-ojMYuQ/o.jpg", "categories": [{"alias": "bars", "title": "Bars"}], "display_phone": "(212) 307-7536", "phone": "+12123077536", "id": "xydPj_xtAqlIEz4q8RFNUw", "is_closed": false, "location": {"city": "New York", "display_address": ["401 W 48th St", "New York, NY 10036"], "country": "US", "address2": "", "address3": "", "state": "NY", "address1": "401 W 48th St", "zip_code": "10036"}}]}