{"region": {"center": {"latitude": 40.7175878725, "longitude": -73.9573135904}}, "total": 4100, "businesses": [{"rating": 5.0, "review_count": 1, "name": "Clyde's Caribbean", "transactions": [], "url": "https://www.yelp.com/biz/clydes-caribbean-brooklyn?adjust_creative=yhLoLzsNXKw40xZ5RCWPpA&utm_campaign=yelp_api_v3&utm_medium=api_v3_business_search&utm_source=yhLoLzsNXKw40xZ5RCWPpA", "distance": 62.56858474043718, "coordinates": {"latitude": 40.71798, "longitude": -73.95667}, "alias": "clydes-caribbean-brooklyn", "image_url": "", "categories": [{"alias": "tikibars", "title": "Tiki Bars"}], "display_phone": "(979) 276-3528", "phone": "+19792763528", "id": "tD2QlsEgXVH9lB-6snmcgQ", "is_closed": false, "location": {"city": "Brooklyn", "display_address": ["178 N 8th St", "Brooklyn, NY 11211"], "country": "US", "address2": "", "address3": null, "state": "NY", "address1": "178 N 8th St", "zip_code": "11211"}}]}