{"region": {"center": {"latitude": 40.7109130499, "longitude": -73.9514888835}}, "total": 4100, "businesses": [{"rating": 3.0, "review_count": 23, "name": "Abba Bar and Grill", "transactions": ["pickup", "delivery"], "url": "https://www.yelp.com/biz/abba-bar-and-grill-williamsburg?adjust_creative=yhLoLzsNXKw40xZ5RCWPpA&utm_campaign=yelp_api_v3&utm_medium=api_v3_business_search&utm_source=yhLoLzsNXKw40xZ5RCWPpA", "price": "$$", "distance": 14.384645204974333, "coordinates": {"latitude": 40.7107876994365, "longitude": -73.9515310662704}, "alias": "abba-bar-and-grill-williamsburg", "image_url": "https://s3-media3.fl.yelpcdn.com/bphoto/mycS_Ca69nS1SUJ6LTuiYA/o.jpg", "categories": [{"alias": "bars", "title": "Bars"}, {"alias": "tradamerican", "title": "American (Traditional)"}], "display_phone": "(347) 844-9655", "phone": "+13478449655", "id": "k0F-W3ks-SPF6iataLfwPQ", "is_closed": false, "location": {"city": "Williamsburg", "display_address": ["492 Grand St", "Williamsburg, NY 11211"], "country": "US", "address2": "", "address3": "", "state": "NY", "address1": "492 Grand St", "zip_code": "11211"}}]}