{"region": {"center": {"latitude": 40.7337799915, "longitude": -73.9806451843}}, "total": 4100, "businesses": [{"rating": 3.5, "review_count": 402, "name": "Petite Abeille", "transactions": ["pickup", "delivery"], "url": "https://www.yelp.com/biz/petite-abeille-new-york-5?adjust_creative=yhLoLzsNXKw40xZ5RCWPpA&utm_campaign=yelp_api_v3&utm_medium=api_v3_business_search&utm_source=yhLoLzsNXKw40xZ5RCWPpA", "price": "$$", "distance": 165.17207950892475, "coordinates": {"latitude": 40.7350392676359, "longitude": -73.9796054363251}, "alias": "petite-abeille-new-york-5", "image_url": "https://s3-media2.fl.yelpcdn.com/bphoto/an0To7IyoQ-T5oR8vwCEFw/o.jpg", "categories": [{"alias": "belgian", "title": "Belgian"}, {"alias": "bars", "title": "Bars"}, {"alias": "breakfast_brunch", "title": "Breakfast & Brunch"}], "display_phone": "(212) 727-1505", "phone": "+12127271505", "id": "PhEuVS74xQsDrFXWVH21Xg", "is_closed": false, "location": {"city": "New York", "display_address": ["401 E 20th St", "New York, NY 10010"], "country": "US", "address2": null, "address3": "", "state": "NY", "address1": "401 E 20th St", "zip_code": "10010"}}]}