{"region": {"center": {"latitude": 40.7110058947, "longitude": -73.9653687362}}, "total": 4100, "businesses": [{"rating": 4.0, "review_count": 440, "name": "Bembe", "transactions": [], "url": "https://www.yelp.com/biz/bembe-brooklyn?adjust_creative=yhLoLzsNXKw40xZ5RCWPpA&utm_campaign=yelp_api_v3&utm_medium=api_v3_business_search&utm_source=yhLoLzsNXKw40xZ5RCWPpA", "price": "$$", "distance": 15.075062895495426, "coordinates": {"latitude": 40.7110261023422, "longitude": -73.9651918794702}, "alias": "bembe-brooklyn", "image_url": "https://s3-media1.fl.yelpcdn.com/bphoto/vbHbYI2Rb6mtpc8gTinJbg/o.jpg", "categories": [{"alias": "danceclubs", "title": "Dance Clubs"}], "display_phone": "(718) 387-5389", "phone": "+17183875389", "id": "TZ4x0TUE5cIjwH2Qk6VJRQ", "is_closed": false, "location": {"city": "Brooklyn", "display_address": ["81 S 6th St", "Brooklyn, NY 11249"], "country": "US", "address2": "", "address3": "", "state": "NY", "address1": "81 S 6th St", "zip_code": "11249"}}]}