{"region": {"center": {"latitude": 40.7210122862, "longitude": -73.987077616}}, "total": 4000, "businesses": [{"rating": 4.0, "review_count": 2, "name": "Tico's Tequila Bar", "transactions": [], "url": "https://www.yelp.com/biz/ticos-tequila-bar-new-york?adjust_creative=yhLoLzsNXKw40xZ5RCWPpA&utm_campaign=yelp_api_v3&utm_medium=api_v3_business_search&utm_source=yhLoLzsNXKw40xZ5RCWPpA", "price": "$$$", "distance": 36.81467778970927, "coordinates": {"latitude": 40.7207565, "longitude": -73.9872284}, "alias": "ticos-tequila-bar-new-york", "image_url": "https://s3-media1.fl.yelpcdn.com/bphoto/7rYBX02RaKgA6f5hSjp1eA/o.jpg", "categories": [{"alias": "cocktailbars", "title": "Cocktail Bars"}], "display_phone": "(212) 219-2000", "phone": "+12122192000", "id": "dCUGRMLTI3Jc52aSw1aWFw", "is_closed": false, "location": {"city": "New York", "display_address": ["151 Essex St", "Underneath Tijuana Picnic", "New York, NY 10002"], "country": "US", "address2": "", "address3": "Underneath Tijuana Picnic", "state": "NY", "address1": "151 Essex St", "zip_code": "10002"}}]}