{"region": {"center": {"latitude": 40.7152183625, "longitude": -74.0103023787}}, "total": 3900, "businesses": [{"rating": 3.0, "review_count": 172, "name": "Warren 77", "transactions": ["delivery", "pickup"], "url": "https://www.yelp.com/biz/warren-77-new-york-2?adjust_creative=yhLoLzsNXKw40xZ5RCWPpA&utm_campaign=yelp_api_v3&utm_medium=api_v3_business_search&utm_source=yhLoLzsNXKw40xZ5RCWPpA", "price": "$$", "distance": 22.621732989321156, "coordinates": {"latitude": 40.71513, "longitude": -74.01031}, "alias": "warren-77-new-york-2", "image_url": "https://s3-media3.fl.yelpcdn.com/bphoto/AQarhi8cwhElrPQsOK3gpw/o.jpg", "categories": [{"alias": "sportsbars", "title": "Sports Bars"}, {"alias": "tradamerican", "title": "American (Traditional)"}], "display_phone": "(212) 227-8994", "phone": "+12122278994", "id": "0wsA6vaHKbIuCt9yUxc8Jg", "is_closed": false, "location": {"city": "New York", "display_address": ["77 Warren St", "New York, NY 10007"], "country": "US", "address2": "", "address3": "", "state": "NY", "address1": "77 Warren St", "zip_code": "10007"}}]}