{"region": {"center": {"latitude": 40.5874043756, "longitude": -73.8098210348}}, "total": 106, "businesses": [{"rating": 4.0, "review_count": 112, "name": "Rockaway Beach Surf Club", "transactions": [], "url": "https://www.yelp.com/biz/rockaway-beach-surf-club-far-rockaway?adjust_creative=yhLoLzsNXKw40xZ5RCWPpA&utm_campaign=yelp_api_v3&utm_medium=api_v3_business_search&utm_source=yhLoLzsNXKw40xZ5RCWPpA", "price": "$", "distance": 248.86285909981862, "coordinates": {"latitude": 40.58884, "longitude": -73.81211}, "alias": "rockaway-beach-surf-club-far-rockaway", "image_url": "https://s3-media4.fl.yelpcdn.com/bphoto/X5idXHU9bCo9FvwXkQXAyw/o.jpg", "categories": [{"alias": "venues", "title": "Venues & Event Spaces"}, {"alias": "tacos", "title": "Tacos"}, {"alias": "cocktailbars", "title": "Cocktail Bars"}], "display_phone": "", "phone": "", "id": "TDIcuWKcv2sl34oK5eOXAQ", "is_closed": false, "location": {"city": "Far Rockaway", "display_address": ["302 Beach 87th St", "Far Rockaway, NY 11693"], "country": "US", "address2": "", "address3": "", "state": "NY", "address1": "302 Beach 87th St", "zip_code": "11693"}}]}