{"region": {"center": {"latitude": 40.7247342129, "longitude": -73.9873907721}}, "total": 4100, "businesses": [{"rating": 2.5, "review_count": 310, "name": "Karma", "transactions": [], "url": "https://www.yelp.com/biz/karma-new-york?adjust_creative=yhLoLzsNXKw40xZ5RCWPpA&utm_campaign=yelp_api_v3&utm_medium=api_v3_business_search&utm_source=yhLoLzsNXKw40xZ5RCWPpA", "price": "$$", "distance": 31.932342635236314, "coordinates": {"latitude": 40.72493, "longitude": -73.98765}, "alias": "karma-new-york", "image_url": "https://s3-media2.fl.yelpcdn.com/bphoto/rN4Fty-hupIsuR7ega1UPA/o.jpg", "categories": [{"alias": "lounges", "title": "Lounges"}, {"alias": "hookah_bars", "title": "Hookah Bars"}], "display_phone": "(212) 677-3160", "phone": "+12126773160", "id": "SNgPlsWJw0Zpmyi4e8VD4g", "is_closed": false, "location": {"city": "New York", "display_address": ["51 1st Ave", "New York, NY 10003"], "country": "US", "address2": "", "address3": "", "state": "NY", "address1": "51 1st Ave", "zip_code": "10003"}}]}