{"region": {"center": {"latitude": 40.7298687325, "longitude": -73.9807437382}}, "total": 4100, "businesses": [{"rating": 4.0, "review_count": 594, "name": "Fat Buddha", "transactions": [], "url": "https://www.yelp.com/biz/fat-buddha-new-york?adjust_creative=yhLoLzsNXKw40xZ5RCWPpA&utm_campaign=yelp_api_v3&utm_medium=api_v3_business_search&utm_source=yhLoLzsNXKw40xZ5RCWPpA", "price": "$$", "distance": 13.186393941183812, "coordinates": {"latitude": 40.7298105, "longitude": -73.9805949}, "alias": "fat-buddha-new-york", "image_url": "https://s3-media3.fl.yelpcdn.com/bphoto/OZ4LvWCnQ9Pf6bWLYYx02w/o.jpg", "categories": [{"alias": "bars", "title": "Bars"}, {"alias": "asianfusion", "title": "Asian Fusion"}, {"alias": "korean", "title": "Korean"}], "display_phone": "(212) 598-0500", "phone": "+12125980500", "id": "iXmDaPsgylG1kHPLli15MQ", "is_closed": false, "location": {"city": "New York", "display_address": ["212 Ave A", "New York, NY 10009"], "country": "US", "address2": "", "address3": "", "state": "NY", "address1": "212 Ave A", "zip_code": "10009"}}]}