{"region": {"center": {"latitude": 40.7604566827, "longitude": -73.9837309673}}, "total": 4000, "businesses": [{"rating": 3.5, "review_count": 285, "name": "Playwright Tavern & Restaurant", "transactions": [], "url": "https://www.yelp.com/biz/playwright-tavern-and-restaurant-new-york-3?adjust_creative=yhLoLzsNXKw40xZ5RCWPpA&utm_campaign=yelp_api_v3&utm_medium=api_v3_business_search&utm_source=yhLoLzsNXKw40xZ5RCWPpA", "price": "$$", "distance": 36.21252439631719, "coordinates": {"latitude": 40.760478, "longitude": -73.98416}, "alias": "playwright-tavern-and-restaurant-new-york-3", "image_url": "https://s3-media4.fl.yelpcdn.com/bphoto/MURUkemb1VVJKAkx6sdIDQ/o.jpg", "categories": [{"alias": "tradamerican", "title": "American (Traditional)"}, {"alias": "irish_pubs", "title": "Irish Pub"}], "display_phone": "(212) 262-9229", "phone": "+12122629229", "id": "httHQj4gGRsgFAh3y65jtg", "is_closed": false, "location": {"city": "New York", "display_address": ["202 W 49th St", "New York, NY 10019"], "country": "US", "address2": null, "address3": "", "state": "NY", "address1": "202 W 49th St", "zip_code": "10019"}}]}