{"region": {"center": {"latitude": 40.7324970585, "longitude": -74.0018329711}}, "total": 4000, "businesses": [{"rating": 3.5, "review_count": 503, "name": "Down the Hatch", "transactions": ["delivery", "pickup"], "url": "https://www.yelp.com/biz/down-the-hatch-new-york?adjust_creative=yhLoLzsNXKw40xZ5RCWPpA&utm_campaign=yelp_api_v3&utm_medium=api_v3_business_search&utm_source=yhLoLzsNXKw40xZ5RCWPpA", "price": "$", "distance": 17.351253098387087, "coordinates": {"latitude": 40.73247, "longitude": -74.00163}, "alias": "down-the-hatch-new-york", "image_url": "https://s3-media3.fl.yelpcdn.com/bphoto/wtROTWcl47Hc2MlgCoRqTw/o.jpg", "categories": [{"alias": "tradamerican", "title": "American (Traditional)"}, {"alias": "sportsbars", "title": "Sports Bars"}, {"alias": "chicken_wings", "title": "Chicken Wings"}], "display_phone": "(212) 627-9747", "phone": "+12126279747", "id": "_owMBYfzT9dO7FXGXXzXqA", "is_closed": false, "location": {"city": "New York", "display_address": ["179 W 4th St", "New York, NY 10014"], "country": "US", "address2": "", "address3": "", "state": "NY", "address1": "179 W 4th St", "zip_code": "10014"}}]}