{"region": {"center": {"latitude": 40.7248371632, "longitude": -73.978320753}}, "total": 4100, "businesses": [{"rating": 2.5, "review_count": 8, "name": "Jolie's NYC", "transactions": [], "url": "https://www.yelp.com/biz/jolies-nyc-new-york?adjust_creative=yhLoLzsNXKw40xZ5RCWPpA&utm_campaign=yelp_api_v3&utm_medium=api_v3_business_search&utm_source=yhLoLzsNXKw40xZ5RCWPpA", "price": "$$", "distance": 21.323198223305813, "coordinates": {"latitude": 40.724933, "longitude": -73.978538}, "alias": "jolies-nyc-new-york", "image_url": "https://s3-media2.fl.yelpcdn.com/bphoto/P09wiORneptcYv2S5J9FuQ/o.jpg", "categories": [{"alias": "bars", "title": "Bars"}, {"alias": "djs", "title": "DJs"}], "display_phone": "(212) 505-3468", "phone": "+12125053468", "id": "QFmzOkrBjtrkRSQJQnVDQw", "is_closed": false, "location": {"city": "New York", "display_address": ["129 Ave C", "New York, NY 10009"], "country": "US", "address2": null, "address3": "", "state": "NY", "address1": "129 Ave C", "zip_code": "10009"}}]}