{"region": {"center": {"latitude": 40.6516057515, "longitude": -73.9331091938}}, "total": 2000, "businesses": [{"rating": 4.0, "review_count": 2, "name": "Charl-Ena Chateau", "transactions": [], "url": "https://www.yelp.com/biz/charl-ena-chateau-brooklyn?adjust_creative=yhLoLzsNXKw40xZ5RCWPpA&utm_campaign=yelp_api_v3&utm_medium=api_v3_business_search&utm_source=yhLoLzsNXKw40xZ5RCWPpA", "distance": 684.5197616479298, "coordinates": {"latitude": 40.650962, "longitude": -73.941154}, "alias": "charl-ena-chateau-brooklyn", "image_url": "https://s3-media2.fl.yelpcdn.com/bphoto/fgLNfRWRFI2bNZsQctQQLA/o.jpg", "categories": [{"alias": "newamerican", "title": "American (New)"}, {"alias": "bars", "title": "Bars"}], "display_phone": "(718) 941-4777", "phone": "+17189414777", "id": "TX3uUuu_ob5DNlNDf1TbOw", "is_closed": false, "location": {"city": "Brooklyn", "display_address": ["3820 Church Ave", "Brooklyn, NY 11203"], "country": "US", "address2": "", "address3": "", "state": "NY", "address1": "3820 Church Ave", "zip_code": "11203"}}]}