{"region": {"center": {"latitude": 40.7500736523, "longitude": -73.9863681919}}, "total": 4100, "businesses": [{"rating": 4.0, "review_count": 432, "name": "Karaoke DUET 35", "transactions": [], "url": "https://www.yelp.com/biz/karaoke-duet-35-new-york?adjust_creative=yhLoLzsNXKw40xZ5RCWPpA&utm_campaign=yelp_api_v3&utm_medium=api_v3_business_search&utm_source=yhLoLzsNXKw40xZ5RCWPpA", "price": "$$", "distance": 27.557675219317435, "coordinates": {"latitude": 40.750281, "longitude": -73.986189}, "alias": "karaoke-duet-35-new-york", "image_url": "https://s3-media2.fl.yelpcdn.com/bphoto/EvmP4NUEfq0PKMH68O-wdQ/o.jpg", "categories": [{"alias": "karaoke", "title": "Karaoke"}, {"alias": "musicvenues", "title": "Music Venues"}], "display_phone": "(646) 473-0826", "phone": "+16464730826", "id": "9ZLb43mkz3Td39nfS8ow4Q", "is_closed": false, "location": {"city": "New York", "display_address": ["53 W 35th St", "Fl 2", "New York, NY 10001"], "country": "US", "address2": "Fl 2", "address3": "", "state": "NY", "address1": "53 W 35th St", "zip_code": "10001"}}]}